pages/models.py
pages/fields.py
pages/mixins.py
pages/__init__.py
pages/serializers.py
pages/views.py
pages/admin.py
pages/tests/models.py
pages/tests/__init__.py
pages/tests/test_fields.py
pages/tests/factories.py
pages/tests/test_urls.py
pages/tests/test_models.py
pages/tests/settings.py
pages/tests/utils.py
pages/tests/test_serializers.py
pages/tests/run.py
pages/tests/test_views.py
pages/tests/urls.py
pages/tests/migrations/__init__.py
pages/tests/migrations/0001_initial.py
pages/tests/testmigrations/__init__.py
pages/tests/testmigrations/pages/__init__.py
pages/tests/testmigrations/pages/0001_initial.py
pages/tests/testmigrations/feincms/__init__.py
pages/tests/testmigrations/feincms/0001_initial.py
pages/tests/testmigrations/api/__init__.py
pages/tests/testmigrations/api/0001_initial.py
pages/utils/__init__.py
pages/utils/tests/__init__.py
pages/utils/tests/test_utils.py
pages/urls/__init__.py
pages/urls/group.py
pages/urls/page.py
pages/migrations/__init__.py
pages/migrations/0001_initial.py
feincms_pages_api-1.3.0.dist-info/top_level.txt
feincms_pages_api-1.3.0.dist-info/DESCRIPTION.rst
feincms_pages_api-1.3.0.dist-info/RECORD
feincms_pages_api-1.3.0.dist-info/metadata.json
feincms_pages_api-1.3.0.dist-info/METADATA
feincms_pages_api-1.3.0.dist-info/WHEEL
