Metadata-Version: 2.0
Name: feincms-pages-api
Version: 1.3.0
Summary: UNKNOWN
Home-page: https://github.com/incuna/feincms-pages-api/
Author: Incuna Ltd
Author-email: admin@incuna.com
License: BSD
Platform: UNKNOWN
Classifier: Development Status :: 5 - Production/Stable
Classifier: Environment :: Web Environment
Classifier: Framework :: Django
Classifier: Intended Audience :: Developers
Classifier: License :: OSI Approved :: BSD License
Classifier: Operating System :: OS Independent
Classifier: Programming Language :: Python
Classifier: Programming Language :: Python :: 2
Classifier: Programming Language :: Python :: 2.7
Classifier: Programming Language :: Python :: 3
Classifier: Programming Language :: Python :: 3.3
Classifier: Topic :: Internet :: WWW/HTTP :: Dynamic Content
Classifier: Topic :: Software Development
Classifier: Topic :: Software Development :: Libraries :: Application Frameworks
Requires-Dist: djangorestframework (>=3.0.5,<3.4)
Requires-Dist: FeinCMS (>=1.9,<1.12)
Requires-Dist: django-orderable (>=2.0.1,<4)
Requires-Dist: feincms-extensions (>=0.1.0,<1)
